oqd_cloud/__init__.py
oqd_cloud/client.py
oqd_cloud/provider.py
oqd_cloud/server/__init__.py
oqd_cloud/server/app.py
oqd_cloud/server/database.py
oqd_cloud/server/jobqueue.py
oqd_cloud/server/main.py
oqd_cloud/server/model.py
oqd_cloud/server/route/__init__.py
oqd_cloud/server/route/auth.py
oqd_cloud/server/route/job.py
oqd_cloud/server/route/user.py
oqd_cloud-0.1.0.dist-info/LICENSE
oqd_cloud-0.1.0.dist-info/METADATA
oqd_cloud-0.1.0.dist-info/NOTICE
oqd_cloud-0.1.0.dist-info/WHEEL
oqd_cloud-0.1.0.dist-info/top_level.txt
oqd_cloud-0.1.0.dist-info/RECORD
