Metadata-Version: 2.1
Name: oqd-cloud
Version: 0.1.0
License: Apache 2.0
Project-URL: Homepage, https://github.com/OpenQuantumDesign/oqd-cloud
Project-URL: Repository, https://github.com/OpenQuantumDesign/oqd-cloud.git
Project-URL: Issues, https://github.com/OpenQuantumDesign/oqd-cloud/issues
Keywords: quantum,computing,simulation,cloud,server
Classifier: Development Status :: 3 - Alpha
Classifier: Intended Audience :: Science/Research 
Classifier: Topic :: Scientific/Engineering :: Physics
Classifier: Topic :: Scientific/Engineering :: Information Analysis
Classifier: License :: OSI Approved :: Apache Software License
Classifier: Programming Language :: Python :: 3
Classifier: Programming Language :: Python :: 3.10
Classifier: Programming Language :: Python :: 3.11
Classifier: Programming Language :: Python :: 3.12
Requires-Python: >=3.10
License-File: LICENSE
License-File: NOTICE
Requires-Dist: requests
Requires-Dist: pydantic>=2.4
Requires-Dist: numpy~=1.0
Requires-Dist: oqd-compiler-infrastructure
Requires-Dist: oqd-core
Requires-Dist: oqd-analog-emulator
Provides-Extra: docs
Requires-Dist: pymdown-extensions; extra == "docs"
Requires-Dist: mkdocstrings; extra == "docs"
Requires-Dist: mkdocs-material; extra == "docs"
Requires-Dist: mkdocstrings-python; extra == "docs"
Provides-Extra: server
Requires-Dist: pydantic>=2.4; extra == "server"
Requires-Dist: qutip~=5.0.1; extra == "server"
Requires-Dist: asyncpg; extra == "server"
Requires-Dist: uvicorn; extra == "server"
Requires-Dist: python-jose; extra == "server"
Requires-Dist: passlib; extra == "server"
Requires-Dist: python-multipart; extra == "server"
Requires-Dist: oqd-compiler-infrastructure; extra == "server"
Requires-Dist: oqd-core; extra == "server"
Requires-Dist: oqd-analog-emulator; extra == "server"
Provides-Extra: test
Requires-Dist: unittest-prettify; extra == "test"
